pyproject.toml
setup.py
rapid/__init__.py
rapid/auth.py
rapid/exceptions.py
rapid/rapid.py
rapid/items/__init__.py
rapid/items/query.py
rapid/items/schema.py
rapid/patterns/__init__.py
rapid/patterns/dataset.py
rapid/utils/__init__.py
rapid/utils/constants.py
rapid_sdk.egg-info/PKG-INFO
rapid_sdk.egg-info/SOURCES.txt
rapid_sdk.egg-info/dependency_links.txt
rapid_sdk.egg-info/requires.txt
rapid_sdk.egg-info/top_level.txt
test/test_utils.py