Metadata-Version: 2.4
Name: rapid-sdk
Version: 0.1.13
Summary: A python sdk for the rAPId API
Home-page: https://github.com/no10ds/rapid
Author: Lewis Card
Author-email: lcard@no10.gov.uk
License: MIT
Requires-Dist: pandas
Requires-Dist: requests
Requires-Dist: deepdiff
Requires-Dist: pyarrow
Requires-Dist: pydantic
Dynamic: author
Dynamic: author-email
Dynamic: home-page
Dynamic: license
Dynamic: requires-dist
Dynamic: summary
